[
    {
        "id_factura":1,
        "id_producto":1,
        "cantidad":1,
        "precio_unitario":450000.0
    },
    {
        "id_factura":1,
        "id_producto":3,
        "cantidad":1,
        "precio_unitario":120000.0
    },
    {
        "id_factura":1,
        "id_producto":5,
        "cantidad":1,
        "precio_unitario":8500.0
    },
    {
        "id_factura":2,
        "id_producto":2,
        "cantidad":1,
        "precio_unitario":380000.0
    },
    {
        "id_factura":2,
        "id_producto":5,
        "cantidad":1,
        "precio_unitario":8500.0
    },
    {
        "id_factura":5,
        "id_producto":1,
        "cantidad":1,
        "precio_unitario":450000.0
    },
    {
        "id_factura":5,
        "id_producto":6,
        "cantidad":1,
        "precio_unitario":38000.0
    },
    {
        "id_factura":5,
        "id_producto":7,
        "cantidad":1,
        "precio_unitario":22000.0
    },
    {
        "id_factura":10,
        "id_producto":11,
        "cantidad":79,
        "precio_unitario":100000.0
    }
]